chemio/__init__.py
chemio/config.conf
chemio/main.py
chemio/molecule.py
chemio/supported_writetypes.py
chemio/supported_writetypes.txt
chemio/version.py
chemio/cli/__init__.py
chemio/cli/convert.py
chemio/cli/info.py
chemio/cli/main.py
chemio/cli/utils.py
chemio-2.0.0.dist-info/LICENSE
chemio-2.0.0.dist-info/METADATA
chemio-2.0.0.dist-info/WHEEL
chemio-2.0.0.dist-info/entry_points.txt
chemio-2.0.0.dist-info/top_level.txt
chemio-2.0.0.dist-info/RECORD
